kivysome/__init__.py
kivysome/iconfonts.py
kivysome/kivysome.py
kivysome-0.2.1.dist-info/LICENSE
kivysome-0.2.1.dist-info/WHEEL
kivysome-0.2.1.dist-info/METADATA
kivysome-0.2.1.dist-info/RECORD
