Metadata-Version: 2.1
Name: kivysome
Version: 0.2.1
Summary: Font Awesome 5 Icons for Kivy
Home-page: https://github.com/matfax/kivysome
License: MIT
Keywords: kivy,fa,font,awesome,icons
Author: matfax
Author-email: matthias.fax@gmail.com
Requires-Python: >=3.7,<4.0
Classifier: License :: OSI Approved :: MIT License
Classifier: Programming Language :: Python :: 3
Classifier: Programming Language :: Python :: 3.7
Classifier: Programming Language :: Python :: 3.8
Requires-Dist: lastversion (==1.2.0)
Requires-Dist: mutapath (>=0.16.0,<0.17.0)
Requires-Dist: remotezip (>=0.9.2,<0.10.0)
Requires-Dist: semver (>=2.10.2,<3.0.0)
Requires-Dist: urllib3 (>=1.25.7,<2.0.0)
Project-URL: Repository, https://github.com/matfax/kivysome
